stacklet/client/__init__.py
stacklet/client/sinistral/__init__.py
stacklet/client/sinistral/cli.py
stacklet/client/sinistral/client.py
stacklet/client/sinistral/cognito.py
stacklet/client/sinistral/commands/__init__.py
stacklet/client/sinistral/commands/dump.py
stacklet/client/sinistral/commands/group.py
stacklet/client/sinistral/commands/org.py
stacklet/client/sinistral/commands/policy.py
stacklet/client/sinistral/commands/policy_collections.py
stacklet/client/sinistral/commands/policy_sources.py
stacklet/client/sinistral/commands/projects.py
stacklet/client/sinistral/commands/run.py
stacklet/client/sinistral/commands/scans.py
stacklet/client/sinistral/config.py
stacklet/client/sinistral/context.py
stacklet/client/sinistral/exceptions.py
stacklet/client/sinistral/executor.py
stacklet/client/sinistral/formatter.py
stacklet/client/sinistral/output.py
stacklet/client/sinistral/registry.py
stacklet/client/sinistral/utils.py
stacklet/client/sinistral/vendored/__init__.py
stacklet/client/sinistral/vendored/auth.py
stacklet/client/sinistral/vendored/auth_landing_pages/__init__.py
stacklet/client/sinistral/vendored/auth_landing_pages/fail.html
stacklet/client/sinistral/vendored/auth_landing_pages/ok.html
stacklet_client_sinistral-0.5.32.dist-info/METADATA
stacklet_client_sinistral-0.5.32.dist-info/WHEEL
stacklet_client_sinistral-0.5.32.dist-info/entry_points.txt
stacklet_client_sinistral-0.5.32.dist-info/RECORD
