Metadata-Version: 2.3
Name: stacklet.client.sinistral
Version: 0.5.32
Summary: Sinistral CLI
License: Apache-2.0
Author: Sonny Shi
Author-email: sonny@stacklet.io
Maintainer: Stacklet
Maintainer-email: hello@stacklet.io
Requires-Python: >=3.10.2,<4
Classifier: License :: OSI Approved :: Apache Software License
Classifier: Programming Language :: Python :: 3
Classifier: Programming Language :: Python :: 3.11
Classifier: Programming Language :: Python :: 3.12
Classifier: Programming Language :: Python :: 3.13
Requires-Dist: boto3 (>=1.26.72,<2.0.0)
Requires-Dist: c7n-left (==0.3.32)
Requires-Dist: click (>=8.1.3,<9.0.0)
Requires-Dist: codecov-cli (>=11.1.0,<12.0.0)
Requires-Dist: jmespath (>=1.0.1,<2.0.0)
Requires-Dist: jsonschema (>=4.17.3,<5.0.0)
Requires-Dist: pyjwt (>=2.6.0,<3.0.0)
Requires-Dist: pyrsistent (>=0.19.3,<0.20.0)
Requires-Dist: pyyaml (>=6.0,<7.0)
Requires-Dist: requests (>=2.28.2,<3.0.0)
